odoo8_addon_stock_transport_multi_address-8.0.1.0.0-py2.7-nspkg.pth
odoo8_addon_stock_transport_multi_address-8.0.1.0.0.dist-info/top_level.txt
odoo8_addon_stock_transport_multi_address-8.0.1.0.0.dist-info/WHEEL
odoo8_addon_stock_transport_multi_address-8.0.1.0.0.dist-info/RECORD
odoo8_addon_stock_transport_multi_address-8.0.1.0.0.dist-info/metadata.json
odoo8_addon_stock_transport_multi_address-8.0.1.0.0.dist-info/DESCRIPTION.rst
odoo8_addon_stock_transport_multi_address-8.0.1.0.0.dist-info/METADATA
odoo8_addon_stock_transport_multi_address-8.0.1.0.0.dist-info/namespace_packages.txt
odoo_addons/stock_transport_multi_address/__openerp__.py
odoo_addons/stock_transport_multi_address/__init__.py
odoo_addons/stock_transport_multi_address/README.rst
odoo_addons/stock_transport_multi_address/view/procurement.xml
odoo_addons/stock_transport_multi_address/view/res_partner.xml
odoo_addons/stock_transport_multi_address/view/stock.xml
odoo_addons/stock_transport_multi_address/i18n/es.po
odoo_addons/stock_transport_multi_address/i18n/stock_transport_multi_address.pot
odoo_addons/stock_transport_multi_address/model/stock.py
odoo_addons/stock_transport_multi_address/model/res_partner.py
odoo_addons/stock_transport_multi_address/model/__init__.py
odoo_addons/stock_transport_multi_address/model/procurement.py
odoo_addons/stock_transport_multi_address/static/description/icon.png
